UpdateChromeDriver/__init__.py
UpdateChromeDriver-0.0.3.dist-info/METADATA
UpdateChromeDriver-0.0.3.dist-info/WHEEL
UpdateChromeDriver-0.0.3.dist-info/top_level.txt
UpdateChromeDriver-0.0.3.dist-info/zip-safe
UpdateChromeDriver-0.0.3.dist-info/RECORD
