Metadata-Version: 2.1
Name: UpdateChromeDriver
Version: 0.0.3
Summary: 针对115以上版本的谷歌游览器自动升级selenium驱动。
Author: 小小明
Author-email: 604049322@qq.com
License: GPLv3
Platform: any
Classifier: Programming Language :: Python :: 3
Classifier: License :: OSI Approved :: MIT License
Requires-Python: >=3.6
Requires-Dist: requests
Requires-Dist: tqdm
Requires-Dist: selenium >4.0.0
